segmentApp/__init__.py
segmentApp/admin.py
segmentApp/apps.py
segmentApp/django_analytics.py
segmentApp/middleware.py
segmentApp/models.py
segmentApp/tests.py
segmentApp/utils.py
segmentApp/views.py
segmentApp/migrations/__init__.py
segmentApp/templates/layouts/default/base.html
segmentApp/templates/layouts/snippets/identify.html
segmentApp/templates/layouts/snippets/segment.html
segmentApp-0.1.dist-info/LICENSE
segmentApp-0.1.dist-info/METADATA
segmentApp-0.1.dist-info/WHEEL
segmentApp-0.1.dist-info/top_level.txt
segmentApp-0.1.dist-info/RECORD
